aiotimeout.py
aiotimeout-0.0.4.dist-info/LICENSE
aiotimeout-0.0.4.dist-info/METADATA
aiotimeout-0.0.4.dist-info/WHEEL
aiotimeout-0.0.4.dist-info/top_level.txt
aiotimeout-0.0.4.dist-info/RECORD
