Metadata-Version: 2.1
Name: aiotimeout
Version: 0.0.4
Summary: Timeout context manager for asyncio Python
Home-page: https://github.com/michalc/aiotimeout
Author: Michal Charemza
Author-email: michal@charemza.name
License: UNKNOWN
Platform: UNKNOWN
Classifier: Programming Language :: Python :: 3
Classifier: License :: OSI Approved :: MIT License
Classifier: Operating System :: OS Independent
Classifier: Framework :: AsyncIO
Requires-Python: ~=3.5
